Metadata-Version: 1.0
Name: ch-probability
Version: 0.1
Summary: Gaussian and Binomial distributions
Home-page: UNKNOWN
Author: Carlos Hernandez-Vaquero
Author-email: carloshvp@gmail.com
License: UNKNOWN
Platform: UNKNOWN
